{
  "project_info": {
    "project_number": "88785554627",
    "firebase_url": "https://interiar.firebaseio.com",
    "project_id": "interiar",
    "storage_bucket": "interiar.appspot.com"
  },
  "client": [
    {
      "client_info": {
        "mobilesdk_app_id": "1:88785554627:android:e42299b11293fc0b",
        "android_client_info": {
          "package_name": "com.maaz.interiar"
        }
      },
      "oauth_client": [
        {
          "client_id": "88785554627-20gbiagbij0va3cl0veq049g6v42cd47.apps.googleusercontent.com",
          "client_type": 1,
          "android_info": {
            "package_name": "com.maaz.interiar",
            "certificate_hash": "a8f5ee3124db902e6bcbde8bd36d4d0b31bed32a"
          }
        },
        {
          "client_id": "88785554627-9ge1ev3oh0uep9ikmbk4pmoffhpmgk16.apps.googleusercontent.com",
          "client_type": 3
        }
      ],
      "api_key": [
        {
          "current_key": "AIzaSyBK4-Jmejdg1A3fDC4pewWkgxfIGmWbYOU"
        }
      ],
      "services": {
        "appinvite_service": {
          "other_platform_oauth_client": [
            {
              "client_id": "88785554627-9ge1ev3oh0uep9ikmbk4pmoffhpmgk16.apps.googleusercontent.com",
              "client_type": 3
            }
          ]
        }
      }
    }
  ],
  "configuration_version": "1"
}